<?xml version="1.0" encoding="utf-8"?>
<savedqueries xmlns:xsi="http://www.w3.org/2001/XMLSchema-instance">
  <savedquery>
    <IsCustomizable>1</IsCustomizable>
    <CanBeDeleted>0</CanBeDeleted>
    <isquickfindquery>0</isquickfindquery>
    <isprivate>0</isprivate>
    <isdefault>1</isdefault>
    <savedqueryid>{62c1be0e-613b-4d30-a9fa-7a99e8adae38}</savedqueryid>
    <layoutxml>
      <grid name="ita_itaservicebookings" jump="ita_name" select="1" icon="1" preview="1">
        <row name="ita_itaservicebooking" id="ita_itaservicebookingid">
          <cell name="ita_name" width="146" />
          <cell name="ita_client" width="100" />
          <cell name="ita_authenticationid" width="139" />
        </row>
      </grid>
    </layoutxml>
    <querytype>2</querytype>
    <fetchxml>
      <fetch version="1.0" mapping="logical">
        <entity name="ita_itaservicebooking">
          <attribute name="ita_itaservicebookingid" />
          <attribute name="ita_name" />
          <order attribute="ita_name" descending="false" />
          <filter type="and">
            <condition attribute="statecode" operator="eq" value="0" />
          </filter>
          <attribute name="ita_client" />
          <attribute name="ita_authenticationid" />
        </entity>
      </fetch>
    </fetchxml>
    <IntroducedVersion>1.0</IntroducedVersion>
    <LocalizedNames>
      <LocalizedName description="ITA Service Booking Associated View" languagecode="1033" />
    </LocalizedNames>
  </savedquery>
</savedqueries>