<?xml version="1.0" encoding="utf-8"?>
<optionset Name="ita_subscriptionstatus" localizedName="Subscription Status" xmlns:xsi="http://www.w3.org/2001/XMLSchema-instance">
  <OptionSetType>picklist</OptionSetType>
  <IsGlobal>1</IsGlobal>
  <IntroducedVersion>1.0.0.0</IntroducedVersion>
  <IsCustomizable>1</IsCustomizable>
  <ExternalTypeName></ExternalTypeName>
  <displaynames>
    <displayname description="Subscription Status" languagecode="1033" />
  </displaynames>
  <options>
    <option value="556780000" ExternalValue="">
      <labels>
        <label description="Not Subscribed" languagecode="1033" />
      </labels>
      <Descriptions>
        <Description description="" languagecode="1033" />
      </Descriptions>
    </option>
    <option value="556780001" ExternalValue="">
      <labels>
        <label description="Subscribed" languagecode="1033" />
      </labels>
      <Descriptions>
        <Description description="" languagecode="1033" />
      </Descriptions>
    </option>
    <option value="556780002" ExternalValue="">
      <labels>
        <label description="Unsubscribed" languagecode="1033" />
      </labels>
      <Descriptions>
        <Description description="" languagecode="1033" />
      </Descriptions>
    </option>
  </options>
</optionset>